karta/__init__.py
karta/crs.py
karta/errors.py
karta/examples.py
karta/geodesy.py
karta/raster/__init__.py
karta/raster/_aai.py
karta/raster/_dem.py
karta/raster/_gtiff.py
karta/raster/aaigrid.py
karta/raster/crfuncs.so
karta/raster/grid.py
karta/raster/misc.py
karta/raster/read.py
karta/vector/__init__.py
karta/vector/_cvectorgeo.so
karta/vector/geojson.py
karta/vector/geometry.py
karta/vector/gpx.py
karta/vector/metadata.py
karta/vector/quadtree.py
karta/vector/read.py
karta/vector/shp.py
karta/vector/stats.py
karta/vector/vtk.py
karta/vector/xyfile.py
karta-0.5.0a0.dist-info/DESCRIPTION.rst
karta-0.5.0a0.dist-info/METADATA
karta-0.5.0a0.dist-info/metadata.json
karta-0.5.0a0.dist-info/RECORD
karta-0.5.0a0.dist-info/top_level.txt
karta-0.5.0a0.dist-info/WHEEL
