Metadata-Version: 2.0
Name: karta
Version: 0.5.0a0
Summary: Geospatial analysis in Python
Home-page: http://www.ironicmtn.com/karta.html
Author: Nat Wilson
Author-email: njwilson23@gmail.com
License: MIT License
Download-URL: https://github.com/njwilson23/karta/archive/master.zip
Platform: UNKNOWN
Classifier: Programming Language :: Python :: 2
Classifier: Programming Language :: Python :: 2.7Programming Language :: Python :: 3
Classifier: Programming Language :: Python :: 3.2
Classifier: Programming Language :: Python :: 3.3
Classifier: Programming Language :: Python :: 3.4
Classifier: Development Status :: 4 - Beta
Classifier: Topic :: Scientific/Engineering
Requires-Dist: numpy (>=1.6)
Requires-Dist: pyproj (>=1.9)
Requires-Dist: pyshp (>=1.2)
